{
  "schema": 1,
  "rom": "LineageOS",
  "status": "build_ready",
  "blocked_reasons": [],
  "source_facts": {
    "lineage_devices_url": "https://wiki.lineageos.org/devices/",
    "lineage_wiki_url": "https://wiki.lineageos.org/devices/aurora/",
    "lineage_wiki_files": [
      "https://github.com/LineageOS/lineage_wiki/blob/main/_data/devices/aurora.yml"
    ],
    "download_api_url": "https://download.lineageos.org/api/v2/devices/aurora/builds",
    "latest_official_build": {
      "date": "2026-05-27",
      "datetime": 1779884696,
      "filename": "lineage-22.2-20260527-nightly-aurora-signed.zip",
      "filepath": "/full/aurora/20260527/lineage-22.2-20260527-nightly-aurora-signed.zip",
      "os_patch_level": "2026-05-01",
      "os_sdk_level": 35,
      "ota_property_files": "payload_metadata.bin:3546:144737,payload.bin:3546:1008653948,payload_properties.txt:1008657552:156,apex_info.pb:1753:1157,care_map.pb:2957:542,metadata:69:678,metadata.pb:815:890                         ",
      "sha1": "ae6e639e8dc84258f1952e5b6c7ed1253c658e29",
      "sha256": "dbcabde4cbb046f686bf04c4f709aabf05d7415a7c14a46e2616775f774d9ff6",
      "size": 1008660703,
      "type": "nightly",
      "url": "https://mirrorbits.lineageos.org/full/aurora/20260527/lineage-22.2-20260527-nightly-aurora-signed.zip"
    },
    "names": [
      "Xperia XZ2 Premium"
    ],
    "models": [
      "H8116",
      "H8166"
    ],
    "vendor": "Sony",
    "vendor_short": "sony",
    "architecture": "arm64",
    "current_branch": "22.2",
    "versions": [
      "22.2",
      "22.1",
      "21",
      "20",
      "19.1",
      "18.1"
    ],
    "recovery_partition_name": "boot",
    "device_tree": {
      "repo": "https://github.com/LineageOS/android_device_sony_aurora",
      "ref": "lineage-22.2",
      "validation": "found"
    },
    "kernel_source": {
      "repo": "https://github.com/LineageOS/android_kernel_sony_sdm845",
      "ref": "lineage-22.2",
      "validation": "full_source",
      "version": "4.9"
    },
    "board_config": {
      "files": [
        {
          "repo": "https://github.com/LineageOS/android_device_sony_tama-common",
          "ref": "lineage-22.2",
          "file": "BoardConfigCommon.mk"
        },
        {
          "repo": "https://github.com/LineageOS/android_device_sony_aurora",
          "ref": "lineage-22.2",
          "file": "BoardConfig.mk"
        }
      ],
      "kernel_configs": [
        "tama_aurora_defconfig"
      ],
      "kernel_source_path": "kernel/sony/sdm845",
      "kernel_image_name": "Image.gz-dtb"
    }
  },
  "build": {
    "device": "aurora",
    "vendor": "Sony",
    "vendor_short": "sony",
    "lineage_branch": "lineage-22.2",
    "boot_source_url": "https://mirrorbits.lineageos.org/full/aurora/20260527/lineage-22.2-20260527-nightly-aurora-signed.zip",
    "boot_source_sha256": "dbcabde4cbb046f686bf04c4f709aabf05d7415a7c14a46e2616775f774d9ff6",
    "kernel_repo": "https://github.com/LineageOS/android_kernel_sony_sdm845.git",
    "kernel_ref": "lineage-22.2",
    "arch": "arm64",
    "kernel_configs": [
      "tama_aurora_defconfig"
    ],
    "image_target": "Image.gz-dtb",
    "fragment_path": "config/docker-required.fragment"
  }
}
