{
  "schema": 1,
  "rom": "LineageOS",
  "status": "build_ready",
  "blocked_reasons": [],
  "source_facts": {
    "lineage_devices_url": "https://wiki.lineageos.org/devices/",
    "lineage_wiki_url": "https://wiki.lineageos.org/devices/scorpio/",
    "lineage_wiki_files": [
      "https://github.com/LineageOS/lineage_wiki/blob/main/_data/devices/scorpio.yml"
    ],
    "download_api_url": "https://download.lineageos.org/api/v2/devices/scorpio/builds",
    "latest_official_build": {
      "date": "2026-05-25",
      "datetime": 1779695812,
      "filename": "lineage-22.2-20260525-nightly-scorpio-signed.zip",
      "filepath": "/full/scorpio/20260525/lineage-22.2-20260525-nightly-scorpio-signed.zip",
      "os_patch_level": "2026-05-01",
      "os_sdk_level": 35,
      "ota_property_files": "metadata:69:333,metadata.pb:470:215                 ",
      "sha1": "bd773b89b62a0d0b11494846f5db37046d92afdc",
      "sha256": "ec4c7fe07a2e7557611632b60563a843b0ca1459de318ce2782c698242025054",
      "size": 992521204,
      "type": "nightly",
      "url": "https://mirrorbits.lineageos.org/full/scorpio/20260525/lineage-22.2-20260525-nightly-scorpio-signed.zip"
    },
    "names": [
      "Mi Note 2"
    ],
    "models": [],
    "vendor": "Xiaomi",
    "vendor_short": "xiaomi",
    "architecture": "arm64",
    "current_branch": "22.2",
    "versions": [
      "22.2",
      "18.1",
      "17.1",
      "16.0",
      "15.1"
    ],
    "recovery_partition_name": "recovery",
    "device_tree": {
      "repo": "https://github.com/LineageOS/android_device_xiaomi_scorpio",
      "ref": "lineage-22.2",
      "validation": "found"
    },
    "kernel_source": {
      "repo": "https://github.com/LineageOS/android_kernel_xiaomi_msm8996",
      "ref": "lineage-22.2",
      "validation": "full_source",
      "version": "4.4"
    },
    "board_config": {
      "files": [
        {
          "repo": "https://github.com/LineageOS/android_device_xiaomi_msm8996-common",
          "ref": "lineage-22.2",
          "file": "BoardConfigCommon.mk"
        },
        {
          "repo": "https://github.com/LineageOS/android_device_xiaomi_scorpio",
          "ref": "lineage-22.2",
          "file": "BoardConfig.mk"
        }
      ],
      "kernel_configs": [
        "vendor/xiaomi/mi8996_defconfig",
        "vendor/xiaomi/scorpio.config"
      ],
      "kernel_source_path": "kernel/xiaomi/msm8996",
      "kernel_image_name": "Image.gz-dtb"
    }
  },
  "build": {
    "device": "scorpio",
    "vendor": "Xiaomi",
    "vendor_short": "xiaomi",
    "lineage_branch": "lineage-22.2",
    "boot_source_url": "https://mirrorbits.lineageos.org/full/scorpio/20260525/lineage-22.2-20260525-nightly-scorpio-signed.zip",
    "boot_source_sha256": "ec4c7fe07a2e7557611632b60563a843b0ca1459de318ce2782c698242025054",
    "kernel_repo": "https://github.com/LineageOS/android_kernel_xiaomi_msm8996.git",
    "kernel_ref": "lineage-22.2",
    "arch": "arm64",
    "kernel_configs": [
      "vendor/xiaomi/mi8996_defconfig",
      "vendor/xiaomi/scorpio.config"
    ],
    "image_target": "Image.gz-dtb",
    "fragment_path": "config/docker-required.fragment"
  }
}
