{
  "schema": 1,
  "rom": "LineageOS",
  "status": "build_ready",
  "blocked_reasons": [],
  "source_facts": {
    "lineage_devices_url": "https://wiki.lineageos.org/devices/",
    "lineage_wiki_url": "https://wiki.lineageos.org/devices/devon/",
    "lineage_wiki_files": [
      "https://github.com/LineageOS/lineage_wiki/blob/main/_data/devices/devon.yml"
    ],
    "download_api_url": "https://download.lineageos.org/api/v2/devices/devon/builds",
    "latest_official_build": {
      "date": "2026-05-30",
      "datetime": 1780119849,
      "filename": "lineage-23.2-20260530-nightly-devon-signed.zip",
      "filepath": "/full/devon/20260530/lineage-23.2-20260530-nightly-devon-signed.zip",
      "os_patch_level": "2026-05-01",
      "os_sdk_level": 36,
      "ota_property_files": "payload_metadata.bin:4137:123618,payload.bin:4137:1100079854,payload_properties.txt:1100084049:156,apex_info.pb:1964:1279,care_map.pb:3290:800,metadata:69:677,metadata.pb:814:1102                        ",
      "sha1": "1f0b1e660cdba933a17d1adea5e1be18e6b0e4b9",
      "sha256": "7db6d696efe707c23d04ff9903aeda47595166623514ef5083851c1350102ae9",
      "size": 1100087196,
      "type": "nightly",
      "url": "https://mirrorbits.lineageos.org/full/devon/20260530/lineage-23.2-20260530-nightly-devon-signed.zip"
    },
    "names": [
      "moto g32"
    ],
    "models": [
      "XT2235-1",
      "XT2235-2",
      "XT2235-3"
    ],
    "vendor": "Motorola",
    "vendor_short": "motorola",
    "architecture": "arm64",
    "current_branch": "23.2",
    "versions": [
      "23.2",
      "23.0",
      "22.2",
      "22.1",
      "21",
      "20"
    ],
    "recovery_partition_name": "boot",
    "device_tree": {
      "repo": "https://github.com/LineageOS/android_device_motorola_devon",
      "ref": "lineage-23.2",
      "validation": "found"
    },
    "kernel_source": {
      "repo": "https://github.com/LineageOS/android_kernel_motorola_sm6225",
      "ref": "lineage-23.2",
      "validation": "full_source",
      "version": "4.19"
    },
    "board_config": {
      "files": [
        {
          "repo": "https://github.com/LineageOS/android_device_motorola_sm6225-common",
          "ref": "lineage-23.2",
          "file": "BoardConfigCommon.mk"
        },
        {
          "repo": "https://github.com/LineageOS/android_device_motorola_devon",
          "ref": "lineage-23.2",
          "file": "BoardConfig.mk"
        }
      ],
      "kernel_configs": [
        "vendor/bengal-perf_defconfig",
        "vendor/ext_config/moto-bengal.config",
        "vendor/ext_config/devon-default.config"
      ],
      "kernel_source_path": "kernel/motorola/sm6225",
      "kernel_image_name": "Image"
    }
  },
  "build": {
    "device": "devon",
    "vendor": "Motorola",
    "vendor_short": "motorola",
    "lineage_branch": "lineage-23.2",
    "boot_source_url": "https://mirrorbits.lineageos.org/full/devon/20260530/lineage-23.2-20260530-nightly-devon-signed.zip",
    "boot_source_sha256": "7db6d696efe707c23d04ff9903aeda47595166623514ef5083851c1350102ae9",
    "kernel_repo": "https://github.com/LineageOS/android_kernel_motorola_sm6225.git",
    "kernel_ref": "lineage-23.2",
    "arch": "arm64",
    "kernel_configs": [
      "vendor/bengal-perf_defconfig",
      "vendor/ext_config/moto-bengal.config",
      "vendor/ext_config/devon-default.config"
    ],
    "image_target": "Image",
    "fragment_path": "config/docker-required.fragment"
  }
}
